reporty/__init__.py
reporty/_reporty.py
reporty/templates/basic_theme.yaml
reporty/templates/green_theme.yaml
reporty/templates/red_stripes.yaml
reporty/templates/red_theme.yaml
reporty-0.1.91.dist-info/METADATA
reporty-0.1.91.dist-info/WHEEL
reporty-0.1.91.dist-info/top_level.txt
reporty-0.1.91.dist-info/RECORD
