Metadata-Version: 2.1
Name: reporty
Version: 0.1.91
Summary: Reporty is a python library that contains useful functions for organizing and distributing visual data
Home-page: https://github.com/asboyer2/reporty
Author: Andrew Boyer & Ben Tengelsen
Author-email: reportylib@gmail.com
License: BSD
Keywords: report,email,plot,graph,embed
Platform: UNKNOWN
Requires-Python: >=3.5
Requires-Dist: pyaml
